edugenome/__init__.py
edugenome/fourby4.py
edugenome/linear.py
edugenome/sum20.py
edugenome-0.2.8.dist-info/METADATA
edugenome-0.2.8.dist-info/WHEEL
edugenome-0.2.8.dist-info/top_level.txt
edugenome-0.2.8.dist-info/RECORD
